ecommerce_api_client/__init__.py
ecommerce_api_client/auth.py
ecommerce_api_client/client.py
ecommerce_api_client/exceptions.py
edx_ecommerce_api_client-1.1.2.dist-info/DESCRIPTION.rst
edx_ecommerce_api_client-1.1.2.dist-info/METADATA
edx_ecommerce_api_client-1.1.2.dist-info/RECORD
edx_ecommerce_api_client-1.1.2.dist-info/WHEEL
edx_ecommerce_api_client-1.1.2.dist-info/metadata.json
edx_ecommerce_api_client-1.1.2.dist-info/top_level.txt
