Metadata-Version: 2.0
Name: edx-ecommerce-api-client
Version: 1.1.2
Summary: Slumber client used to access APIs exposed by the edX E-Commerce Service
Home-page: https://github.com/edx/ecommerce-api-client
Author: edX
Author-email: oscm@edx.org
License: Apache
Keywords: edx ecommerce api client
Platform: UNKNOWN
Classifier: Development Status :: 5 - Production/Stable
Classifier: License :: OSI Approved :: Apache Software License
Classifier: Programming Language :: Python
Classifier: Programming Language :: Python :: 2.7
Classifier: Topic :: Internet
Classifier: Intended Audience :: Developers
Classifier: Environment :: Web Environment
Requires-Dist: PyJWT
Requires-Dist: slumber
